pysortexif/__init__.py
pysortexif/pysortexif.py
pysortexif-0.3.0.dist-info/METADATA
pysortexif-0.3.0.dist-info/WHEEL
pysortexif-0.3.0.dist-info/entry_points.txt
pysortexif-0.3.0.dist-info/top_level.txt
pysortexif-0.3.0.dist-info/RECORD
