Metadata-Version: 2.4
Name: pysortexif
Version: 0.3.0
Summary: Simple package to move photographs to folders, depending on exif timestamp
Author-email: Ruggero Turra <giurrero@gmail.com>
Project-URL: Homepage, https://github.com/wiso/pysortexif
Keywords: exif,photography,sort,timestamp
Classifier: Development Status :: 4 - Beta
Classifier: Intended Audience :: End Users/Desktop
Classifier: Programming Language :: Python :: 3.10
Classifier: Programming Language :: Python :: 3.11
Classifier: Programming Language :: Python :: 3.12
Classifier: Topic :: Software Development :: Libraries :: Python Modules
Requires-Python: >=3.10
Requires-Dist: exifread>=3.3.1
Requires-Dist: pyexiftool>=0.5.6
